cymorph-2.0.dist-info/METADATA
cymorph-2.0.dist-info/WHEEL
cymorph-2.0.dist-info/top_level.txt
cymorph-2.0.dist-info/LICENSE
cymorph-2.0.dist-info/RECORD
cymorph/cython_asymmetry.pyx
cymorph/smoothness.py
cymorph/cython_entropy.cpython-310-x86_64-linux-gnu.so
cymorph/cython_asymmetry.cpython-310-x86_64-linux-gnu.so
cymorph/__init__.cpython-310-x86_64-linux-gnu.so
cymorph/cython_smoothness.cpython-310-x86_64-linux-gnu.so
cymorph/cython_g2.pyx
cymorph/cython_smoothness.pyx
cymorph/concentration.py
cymorph/cython_g2.cpython-310-x86_64-linux-gnu.so
cymorph/g2.py
cymorph/cython_entropy.pyx
cymorph/asymmetry.py
cymorph/__init__.py
cymorph/entropy.py
cymorph/__init__.pyx
