Metadata-Version: 2.1
Name: cymorph
Version: 2.0
Summary: Non-parametric Galaxy Morphology Package
Home-page: https://github.com/igorkolesnikov13/cymorph
Author: Igor Kolesnikov
Author-email: igor.s.kolesnikov@gmail.com
License: MIT
Project-URL: Documentation, https://github.com/igorkolesnikov13/cymorph
Project-URL: Code, https://github.com/igorkolesnikov13/cymorph
Project-URL: Issue tracker, https://github.com/igorkolesnikov13/cymorph/issues
Platform: UNKNOWN
Classifier: Development Status :: 1 - Planning
Classifier: License :: OSI Approved :: MIT License
Classifier: Intended Audience :: Education
Classifier: Intended Audience :: Science/Research
Classifier: Topic :: Scientific/Engineering
Classifier: Topic :: Scientific/Engineering :: Mathematics
Classifier: Natural Language :: English
Classifier: Operating System :: OS Independent
Classifier: Programming Language :: C
Classifier: Programming Language :: Cython
Classifier: Programming Language :: Python
Classifier: Programming Language :: Python :: 3
Classifier: Programming Language :: Python :: 3.5
Classifier: Programming Language :: Python :: 3.6
Classifier: Programming Language :: Python :: 3.7
Classifier: Programming Language :: Python :: 3 :: Only
Classifier: Programming Language :: Python :: Implementation :: CPython
Requires-Python: >=3.5
License-File: LICENSE
Requires-Dist: numpy (>=1.22.1)
Requires-Dist: scipy (>=1.7.3)
Requires-Dist: matplotlib (>=3.5.1)
Requires-Dist: seaborn (>=0.11.2)
Requires-Dist: sep (>=1.2.0)
Provides-Extra: docs
Requires-Dist: sphinx ; extra == 'docs'
Requires-Dist: sphinx-rtd-theme ; extra == 'docs'
